mlserving/__init__.py
mlserving/__version__.py
mlserving/_serving_app.py
mlserving/_state.py
mlserving/api/__init__.py
mlserving/api/request.py
mlserving/api/request_validation.py
mlserving/api/response.py
mlserving/health/__init__.py
mlserving/health/health_check_runner.py
mlserving/health/health_handler.py
mlserving/health/status.py
mlserving/predictors/__init__.py
mlserving/predictors/_base.py
mlserving/predictors/_pipeline.py
mlserving/predictors/_rest_predictor.py
mlserving/predictors/runner.py
mlserving/predictors/utils.py
mlserving/predictors/tensorflow/__init__.py
mlserving/predictors/tensorflow/http.py
mlserving/webframeworks/__init__.py
mlserving/webframeworks/base.py
mlserving/webframeworks/factory.py
mlserving/webframeworks/falcon/__init__.py
mlserving/webframeworks/falcon/error_handler.py
mlserving/webframeworks/falcon/falcon_framework.py
mlserving/webframeworks/falcon/health_resource.py
mlserving/webframeworks/falcon/inference_resource.py
mlserving-0.2.0.dist-info/LICENSE.md
mlserving-0.2.0.dist-info/METADATA
mlserving-0.2.0.dist-info/WHEEL
mlserving-0.2.0.dist-info/top_level.txt
mlserving-0.2.0.dist-info/RECORD
